memcache_status/__init__.py
memcache_status/apps.py
memcache_status/utils.py
memcache_status/static/memcache_status.css
memcache_status/templates/memcache_status/admin_index.html
memcache_status/templates/memcache_status/memcache_status.html
memcache_status/templatetags/__init__.py
memcache_status/templatetags/memcache_status_tags.py
memcache_status/tests/__init__.py
memcache_status/tests/tests.py
memcache_status/tests/testapp/__init__.py
memcache_status/tests/testapp/apps.py
memcache_status/tests/testapp/settings.py
memcache_status/tests/testapp/urls.py
django_memcache_status-2.3.dist-info/LICENSE
django_memcache_status-2.3.dist-info/METADATA
django_memcache_status-2.3.dist-info/WHEEL
django_memcache_status-2.3.dist-info/top_level.txt
django_memcache_status-2.3.dist-info/RECORD
