Metadata-Version: 2.1
Name: django-memcache-status
Version: 2.3
Summary: "A django application that displays the load and other statistics about your memcached instances in the admin."
Home-page: https://github.com/bartTC/django-memcache-status
Author: Martin Mahner
Author-email: martin@mahner.org
License: MIT
Keywords: django,cache,memcache,memcached,statistics
Classifier: Development Status :: 5 - Production/Stable
Classifier: Environment :: Web Environment
Classifier: Intended Audience :: Developers
Classifier: License :: OSI Approved :: MIT License
Classifier: Operating System :: OS Independent
Classifier: Programming Language :: Python
Classifier: Programming Language :: Python :: 3.8
Classifier: Programming Language :: Python :: 3.9
Classifier: Programming Language :: Python :: 3.10
Classifier: Programming Language :: Python :: 3.11
Classifier: Framework :: Django
Requires-Python: >=3.8
License-File: LICENSE
Requires-Dist: django (>=3.2)
